{
  "offset": 24,
  "timestamp": "20241103_050452",
  "extracted_text": "Sanket Sarwade\nData Scientist\nAs a highly motivated and detail-oriented data scientist, I am eager to begin my career in the field of data science. With a solid\nfoundation in statistics, programming, and machine learning techniques, I am well-equipped to tackle complex data problems\nand deliver meaningful insights. Through my academic and personal projects, I have honed my skills in data analysis,\nvisualization, and modeling. I am proficient in using tools such as Python, SQL, and Tableau, and have experience working with\nvarious data sources such as CSV, Excel, and JSON. Additionally, I possess excellent communication skills and a passion for\nlearning, which makes me a valuable team player and a quick learner. I am excited to leverage my skills and knowledge to make a\nmeaningful impact in the field of data science.\nEmail: sanketsarwade111@gmail.com\nAddress: New Cidco, Nashik\nPhone: 7798248452\nDate of birth: Jul 15, 2001\nNationality: Indian\nLink: https://github.com/sanketsarwade\nData Science Project Experience\nThough I don't have any real-life job experience, I have gained valuable hands-on\nexperience in data science through various projects using Kaggle datasets and other\nplatforms. I have worked on a variety of projects related to data cleaning, exploratory data\nanalysis, machine learning, and data visualization.\nData Science Project\nThese projects have allowed me to gain proficiency in programming languages such as\nPython, as well as in tools like SQL and Tableau. Through these projects, I have honed my\nproblem-solving and analytical skills, as well as my ability to work collaboratively in a team\nenvironment. I am excited to bring my passion and experience to a real-world data science\nrole.\nExperience\nPune\nJun 2019 - Sep 2022\nBsc Microbiology\nSinhgad College of Science\nPune\nOct 2022 - Jan 2023\nData Scientist\nData Camp\nEducation\nEnglish\nAdvanced\nNarathi\nNative\nHindi\nNative\nLanguages\nSkills\nPython\nSQL\nMachine Learning\nDeep Learning\nTableau\nData Visualization\nData Management\nLeadership\nHandling Pressure\nCollaboration\nProjects\nHuman Activity Recogination\n•\nEmail Spam\n•\nBreast Cancer Prediction\n•\nAnomaly Detection\n•\nIPL prediction\n•\nCertifications & Courses\nPython\n•\nMachine Leaning\n•\nDeep Leaning\n•\nSQl\n•\nData Science\n•\nTableau\n•\n",
  "analysis": {
    "first_name": "Sanket",
    "last_name": "Sarwade",
    "full_name": "Sanket Sarwade",
    "title": "Data Scientist",
    "address": {
      "formatted_location": "New Cidco, Nashik",
      "city": "Nashik",
      "region": "None",
      "country": "India",
      "postal_code": "None"
    },
    "objective": "As a highly motivated and detail-oriented data scientist, I am eager to begin my career in the field of data science.",
    "date_of_birth": "2001-07-15",
    "place_of_birth": "None",
    "phones": [
      "7798248452"
    ],
    "urls": {
      "GitHub": "https://github.com/sanketsarwade"
    },
    "gender": "None",
    "nationality": "Indian",
    "education_details": [
      {
        "etude_title": "Bsc Microbiology",
        "etablissement_name": "Sinhgad College of Science",
        "start_date": "2019-06",
        "end_date": "2022-09",
        "etude_city": "Pune",
        "etude_region": "None",
        "etude_contry": "India"
      }
    ],
    "total_years_education": "3",
    "work_experience_details": [
      {
        "job_title": "Data Scientist",
        "company_name": "Data Camp",
        "city": "Pune",
        "region": "None",
        "sector_of_activity": "None",
        "start_date": "2022-10",
        "end_date": "2023-01"
      }
    ],
    "total_years_work_experience": "1",
    "skills": [
      "Python",
      "SQL",
      "Machine Learning",
      "Deep Learning",
      "Tableau",
      "Data Visualization",
      "Data Management",
      "Leadership",
      "Handling Pressure",
      "Collaboration"
    ],
    "projects": [
      {
        "name": "Human Activity Recogination",
        "outils": []
      },
      {
        "name": "Email Spam",
        "outils": []
      },
      {
        "name": "Breast Cancer Prediction",
        "outils": []
      },
      {
        "name": "Anomaly Detection",
        "outils": []
      },
      {
        "name": "IPL prediction",
        "outils": []
      }
    ],
    "language": [
      {
        "name": "English",
        "level": "Advanced"
      },
      {
        "name": "Hindi",
        "level": "Native"
      }
    ],
    "certifications": [
      {
        "name": "Python",
        "etablissement_certification": "None",
        "date": "None"
      },
      {
        "name": "Machine Leaning",
        "etablissement_certification": "None",
        "date": "None"
      },
      {
        "name": "Deep Leaning",
        "etablissement_certification": "None",
        "date": "None"
      },
      {
        "name": "SQl",
        "etablissement_certification": "None",
        "date": "None"
      },
      {
        "name": "Data Science",
        "etablissement_certification": "None",
        "date": "None"
      },
      {
        "name": "Tableau",
        "etablissement_certification": "None",
        "date": "None"
      }
    ]
  }
}